mpi_print/__init__.py
mpi_print-0.1.0.dist-info/WHEEL
mpi_print-0.1.0.dist-info/entry_points.txt
mpi_print-0.1.0.dist-info/METADATA
mpi_print-0.1.0.dist-info/RECORD
