Metadata-Version: 2.1
Name: mpi-print
Version: 0.1.0
Summary: <Enter a one-sentence description of this project here.>
Home-page: https://github.com/etijskens/mpi-print
License: MIT
Author: Bert Tijskens
Author-email: engelbert.tijskens@uantwerpen.be
Requires-Python: >=3.7,<4.0
Classifier: License :: OSI Approved :: MIT License
Classifier: Programming Language :: Python :: 3
Classifier: Programming Language :: Python :: 3.7
Classifier: Programming Language :: Python :: 3.8
Classifier: Programming Language :: Python :: 3.9
Classifier: Programming Language :: Python :: 3.10
Classifier: Programming Language :: Python :: 3.11
Project-URL: Repository, https://github.com/etijskens/mpi-print
